AUTHORS.txt
COPYING.txt
ImageMagick-License.txt
MANIFEST.in
README.txt
installer.nsi
isk-daemon.conf
isk-daemon.spec
iskdaemon.py
requirements.txt
setup.py
test_imgdb.py
api-docs/README.txt
api-docs/java-client/README.txt
api-docs/php-client/xml_rpc/full-php-test.php
api-docs/php-client/xml_rpc/simple-client-query-example.php
api-docs/php-client/xml_rpc/xmlrpc.inc
api-docs/python-client/xml_rpc/simple-client.py
api-docs/ruby-client/README.txt
core/__init__.py
core/facades.py
core/imgdbapi.py
core/settings.py
core/statistics.py
core/urldownloader.py
core/utils.py
debian/changelog
debian/compat
debian/control
debian/copyright
debian/docs
debian/isk-daemon.postinst.debhelper
debian/isk-daemon.prerm.debhelper
debian/isk-daemon.substvars
debian/pyversions
debian/rules
debian/source/format
imgSeekLib/ImageDB.py
imgSeekLib/__init__.py
imgSeekLib/bloom_filter.cpp
imgSeekLib/bloom_filter.h
imgSeekLib/daemonize.py
imgSeekLib/haar.cpp
imgSeekLib/haar.h
imgSeekLib/imgdb.cpp
imgSeekLib/imgdb.h
imgSeekLib/imgdb.i
imgSeekLib/imgdb.py
imgSeekLib/memcache.py
imgSeekLib/memoize.py
imgSeekLib/utils.py
isk_daemon.egg-info/PKG-INFO
isk_daemon.egg-info/SOURCES.txt
isk_daemon.egg-info/dependency_links.txt
isk_daemon.egg-info/requires.txt
isk_daemon.egg-info/top_level.txt
plugins/__init__.py
test/__init__.py
test/jmeter.jmx
test/test_api.py
test/data/Copy of DSC00006.JPG
test/data/DSC00006.JPG
test/data/DSC00007.JPG
test/data/DSC00008.JPG
test/data/DSC00009.JPG
test/data/DSC00010.JPG
test/data/DSC00011.JPG
test/data/DSC00014.JPG
test/data/DSC00017.JPG
test/data/DSC00019.JPG
test/data/DSC00021.JPG
test/data/DSC00021b.jpg
test/data/DSC00023.JPG
test/data/DSC00024.JPG
test/data/Gladius.jpg
test/data/bla.gif
test/data/テスト.JPG
ui/__init__.py
ui/admin-gwt/.classpath
ui/admin-gwt/.project
ui/admin-gwt/src/com/fredhat/gwt/xmlrpc/XMLRPC.gwt.xml
ui/admin-gwt/src/com/fredhat/gwt/xmlrpc/client/Base64.java
ui/admin-gwt/src/com/fredhat/gwt/xmlrpc/client/Date.java
ui/admin-gwt/src/com/fredhat/gwt/xmlrpc/client/XmlRpcClient.java
ui/admin-gwt/src/com/fredhat/gwt/xmlrpc/client/XmlRpcException.java
ui/admin-gwt/src/com/fredhat/gwt/xmlrpc/client/XmlRpcRequest.java
