Metadata-Version: 1.1
Name: isk-daemon
Version: 0.9.5
Summary: Server and library for adding content-based (visual) image searching to any image related website or software.
Home-page: http://server.imgseek.net/
Author: Ricardo Niederberger Cabral
Author-email: ricardo.cabral at imgseek.net
License: GPLv2
Download-URL: http://www.imgseek.net/isk-daemon/download
Keywords: imgseek iskdaemon image cbir imagedatabase isk-daemon database searchengine
Platform: Linux
Platform: Windows
Platform: Mac OSX
